{"query":"Python数据分析课程的大纲是什么？（含就业保障）","label":"专业咨询"}
{"query":"什么是线程同步？请用通俗语言解释。（含示例代码）","label":"通用知识"}
{"query":"请写出C++中PCA主成分分析的最佳实践。（含示例代码）","label":"通用知识"}
{"query":"AI工程师实战班培训学费是多少？（企业内训咨询）","label":"专业咨询"}
{"query":"前端开发培训学费是多少？（企业内训咨询）","label":"专业咨询"}
{"query":"请写出C++中矩阵求逆的最佳实践。（含复杂度分析）","label":"通用知识"}
{"query":"大数据工程师有无就业推荐与岗前辅导？（面向在职人员）","label":"专业咨询"}
{"query":"如何用SQL实现虚拟内存？请给出示例代码。（含复杂度分析）","label":"通用知识"}
{"query":"数据库与运维培训学费是多少？（含就业保障）","label":"专业咨询"}
{"query":"请说明随机森林的原理和应用。（通俗解释）","label":"通用知识"}
{"query":"全栈工程师班培训学费是多少？","label":"专业咨询"}
{"query":"产品经理速成在成都有校区吗？","label":"专业咨询"}
{"query":"机器学习实战课程的大纲是什么？（面向初中级学员）","label":"专业咨询"}
{"query":"Python数据分析有无就业推荐与岗前辅导？（面向在职人员）","label":"专业咨询"}
{"query":"如何优化OAuth认证的性能？（请给出示例）","label":"通用知识"}
{"query":"如何优化Lambda表达式的性能？（请给出示例）","label":"通用知识"}
{"query":"请说明二分查找的原理和应用。","label":"通用知识"}
{"query":"请说明RESTful API的原理和应用。（请给出示例）","label":"通用知识"}
{"query":"解释什么是正则表达式并给出示例代码。（请给出示例）","label":"通用知识"}
{"query":"如何在Windows下调试Docker镜像构建相关问题？（通俗解释）","label":"通用知识"}
{"query":"如何在PyCharm中使用单例模式？（通俗解释）","label":"通用知识"}
{"query":"云原生工程师师资力量由谁组成？（是否有企业讲师）（面向在职人员）","label":"专业咨询"}
{"query":"什么是虚拟内存？请用通俗语言解释。（请给出示例）","label":"通用知识"}
{"query":"如何在VSCode中使用复数模与辐角？（含示例代码）","label":"通用知识"}
{"query":"全栈工程师班有无就业推荐与岗前辅导？（面向在职人员）","label":"专业咨询"}
{"query":"什么是归并排序？请用通俗语言解释。（含复杂度分析）","label":"通用知识"}
{"query":"全栈工程师班是否提供面授或线上直播？（含就业保障）","label":"专业咨询"}
{"query":"解释什么是Kubernetes部署并给出示例代码。（通俗解释）","label":"通用知识"}
{"query":"全栈工程师班的上课时间和周期是怎样的？（含就业保障）","label":"专业咨询"}
{"query":"如何在Windows下调试消息队列原理相关问题？","label":"通用知识"}
{"query":"如何在Docker容器下调试K-means聚类相关问题？","label":"通用知识"}
{"query":"移动开发培训学费是多少？（面向初中级学员）","label":"专业咨询"}
{"query":"请写出C++中卷积神经网络的最佳实践。","label":"通用知识"}
{"query":"移动开发是否提供项目实战与源码？（面向在职人员）","label":"专业咨询"}
{"query":"请写出Bash中复数模与辐角的最佳实践。（通俗解释）","label":"通用知识"}
{"query":"什么是线性回归？请用通俗语言解释。（含示例代码）","label":"通用知识"}
{"query":"什么是贝叶斯定理？请用通俗语言解释。（请给出示例）","label":"通用知识"}
{"query":"云原生工程师是否提供面授或线上直播？（企业内训咨询）","label":"专业咨询"}
{"query":"AI工程师实战班培训学费是多少？（面向在职人员）","label":"专业咨询"}
{"query":"产品经理速成在武汉有校区吗？","label":"专业咨询"}
{"query":"全栈工程师班是否提供面授或线上直播？（企业内训咨询）","label":"专业咨询"}
{"query":"云原生工程师是否提供项目实战与源码？（企业内训咨询）","label":"专业咨询"}
{"query":"机器学习实战有无就业推荐与岗前辅导？（企业内训咨询）","label":"专业咨询"}
{"query":"JAVA全栈是否提供面授或线上直播？（面向初中级学员）","label":"专业咨询"}
{"query":"测试工程师是否支持分期付款或企业团报优惠？（面向在职人员）","label":"专业咨询"}
{"query":"AI工程师实战班课程的大纲是什么？（面向在职人员）","label":"专业咨询"}
{"query":"大数据工程师的上课时间和周期是怎样的？（面向在职人员）","label":"专业咨询"}
{"query":"Python数据分析的退款与退费流程是怎样的？（面向初中级学员）","label":"专业咨询"}
{"query":"移动开发课程的大纲是什么？（面向初中级学员）","label":"专业咨询"}
{"query":"数据库与运维师资力量由谁组成？（是否有企业讲师）（面向在职人员）","label":"专业咨询"}
{"query":"大数据工程师的退款与退费流程是怎样的？（企业内训咨询）","label":"专业咨询"}
{"query":"什么是哈希表？请用通俗语言解释。（含示例代码）","label":"通用知识"}
{"query":"测试工程师在成都有校区吗？（面向在职人员）","label":"专业咨询"}
{"query":"如何用Go实现互斥锁？请给出示例代码。（通俗解释）","label":"通用知识"}
{"query":"解释什么是信号量并给出示例代码。","label":"通用知识"}
{"query":"数据库与运维的退款与退费流程是怎样的？（含就业保障）","label":"专业咨询"}
{"query":"产品经理速成在杭州有校区吗？","label":"专业咨询"}
{"query":"测试工程师有无就业推荐与岗前辅导？（面向初中级学员）","label":"专业咨询"}
{"query":"全栈工程师班有无就业推荐与岗前辅导？（企业内训咨询）","label":"专业咨询"}
{"query":"如何用Rust实现混淆矩阵？请给出示例代码。（含复杂度分析）","label":"通用知识"}
{"query":"产品经理速成的退款与退费流程是怎样的？","label":"专业咨询"}
{"query":"如何在Linux下调试归并排序相关问题？（通俗解释）","label":"通用知识"}
{"query":"如何优化Docker镜像构建的性能？（通俗解释）","label":"通用知识"}
{"query":"数据库与运维有无就业推荐与岗前辅导？","label":"专业咨询"}
{"query":"解释什么是支持向量机并给出示例代码。","label":"通用知识"}
{"query":"给出一个TCP三次握手的实际例子并分析。（含复杂度分析）","label":"通用知识"}
{"query":"数据库与运维的退款与退费流程是怎样的？（面向在职人员）","label":"专业咨询"}
{"query":"JAVA全栈在苏州有校区吗？（面向在职人员）","label":"专业咨询"}
{"query":"JAVA全栈的退款与退费流程是怎样的？","label":"专业咨询"}
{"query":"全栈工程师班培训学费是多少？（面向初中级学员）","label":"专业咨询"}
{"query":"什么是正态分布？请用通俗语言解释。（请给出示例）","label":"通用知识"}
{"query":"如何在MacOS下调试贝叶斯定理相关问题？（含示例代码）","label":"通用知识"}
{"query":"请说明消息队列原理的原理和应用。（请给出示例）","label":"通用知识"}
{"query":"如何在VSCode中使用正则表达式？（通俗解释）","label":"通用知识"}
{"query":"大数据工程师在重庆有校区吗？（面向初中级学员）","label":"专业咨询"}
{"query":"前端开发课程的大纲是什么？（含就业保障）","label":"专业咨询"}
{"query":"解释什么是分布式事务并给出示例代码。（通俗解释）","label":"通用知识"}
{"query":"如何在Kubernetes集群下调试RPC原理相关问题？（含复杂度分析）","label":"通用知识"}
{"query":"云原生工程师是否提供项目实战与源码？（面向在职人员）","label":"专业咨询"}
{"query":"前端开发是否提供项目实战与源码？（面向初中级学员）","label":"专业咨询"}
{"query":"JAVA全栈课程的大纲是什么？（面向初中级学员）","label":"专业咨询"}
{"query":"Python数据分析的退款与退费流程是怎样的？（含就业保障）","label":"专业咨询"}
{"query":"云原生工程师课程的大纲是什么？（面向初中级学员）","label":"专业咨询"}
{"query":"给出一个分布式事务的实际例子并分析。（请给出示例）","label":"通用知识"}
{"query":"如何优化线程同步的性能？（请给出示例）","label":"通用知识"}
{"query":"给出一个RPC原理的实际例子并分析。（请给出示例）","label":"通用知识"}
{"query":"什么是梯度下降？请用通俗语言解释。（通俗解释）","label":"通用知识"}
{"query":"什么是线性回归？请用通俗语言解释。","label":"通用知识"}
{"query":"测试工程师在南京有校区吗？（企业内训咨询）","label":"专业咨询"}
{"query":"Python数据分析是否提供面授或线上直播？（面向在职人员）","label":"专业咨询"}
{"query":"如何优化Kubernetes部署的性能？（含复杂度分析）","label":"通用知识"}
{"query":"请比较贝叶斯定理和梯度下降的区别。（通俗解释）","label":"通用知识"}
{"query":"给出一个复利计算的实际例子并分析。（请给出示例）","label":"通用知识"}
{"query":"测试工程师的退款与退费流程是怎样的？（面向在职人员）","label":"专业咨询"}
{"query":"如何在PyCharm中使用A*搜索算法？（通俗解释）","label":"通用知识"}
{"query":"如何优化闭包的性能？（含示例代码）","label":"通用知识"}
{"query":"给出一个HTTPS加密流程的实际例子并分析。（含示例代码）","label":"通用知识"}
{"query":"请写出SQL中归并排序的最佳实践。（请给出示例）","label":"通用知识"}
{"query":"AI工程师实战班培训学费是多少？（面向初中级学员）","label":"专业咨询"}
{"query":"云原生工程师是否支持分期付款或企业团报优惠？（含就业保障）","label":"专业咨询"}
{"query":"如何用SQL实现缓存穿透？请给出示例代码。","label":"通用知识"}
{"query":"云原生工程师的上课时间和周期是怎样的？（面向在职人员）","label":"专业咨询"}
{"query":"数据库与运维是否支持分期付款或企业团报优惠？（企业内训咨询）","label":"专业咨询"}
{"query":"什么是HTTPS加密流程？请用通俗语言解释。","label":"通用知识"}
{"query":"如何用SQL实现回溯算法？请给出示例代码。（请给出示例）","label":"通用知识"}
{"query":"云原生工程师在杭州有校区吗？（含就业保障）","label":"专业咨询"}
{"query":"测试工程师是否提供项目实战与源码？（面向初中级学员）","label":"专业咨询"}
{"query":"JAVA全栈是否支持分期付款或企业团报优惠？（面向在职人员）","label":"专业咨询"}
{"query":"全栈工程师班是否提供项目实战与源码？（含就业保障）","label":"专业咨询"}
{"query":"请写出C++中信息熵的最佳实践。","label":"通用知识"}
{"query":"请写出JavaScript中矩阵求逆的最佳实践。（通俗解释）","label":"通用知识"}
{"query":"移动开发是否提供面授或线上直播？（面向初中级学员）","label":"专业咨询"}
{"query":"移动开发培训学费是多少？","label":"专业咨询"}
{"query":"AI工程师实战班的退款与退费流程是怎样的？（面向在职人员）","label":"专业咨询"}
{"query":"如何优化逻辑回归的性能？","label":"通用知识"}
{"query":"AI工程师实战班的退款与退费流程是怎样的？（企业内训咨询）","label":"专业咨询"}
{"query":"大数据工程师是否支持分期付款或企业团报优惠？（企业内训咨询）","label":"专业咨询"}
{"query":"如何在Git中使用PCA主成分分析？","label":"通用知识"}
{"query":"如何优化Kubernetes部署的性能？","label":"通用知识"}
{"query":"测试工程师师资力量由谁组成？（是否有企业讲师）（企业内训咨询）","label":"专业咨询"}
{"query":"产品经理速成培训学费是多少？（企业内训咨询）","label":"专业咨询"}
{"query":"请写出Java中信号量的最佳实践。（请给出示例）","label":"通用知识"}
{"query":"什么是归并排序？请用通俗语言解释。（请给出示例）","label":"通用知识"}
{"query":"请说明快速排序的原理和应用。（含复杂度分析）","label":"通用知识"}
{"query":"云原生工程师有无就业推荐与岗前辅导？（含就业保障）","label":"专业咨询"}
{"query":"请说明Kubernetes部署的原理和应用。（请给出示例）","label":"通用知识"}
{"query":"如何在Kubernetes集群下调试LRU缓存相关问题？","label":"通用知识"}
{"query":"请写出Java中线性回归的最佳实践。（含复杂度分析）","label":"通用知识"}
{"query":"移动开发培训学费是多少？（面向在职人员）","label":"专业咨询"}
{"query":"数据库与运维是否支持分期付款或企业团报优惠？","label":"专业咨询"}
{"query":"机器学习实战是否支持分期付款或企业团报优惠？（面向在职人员）","label":"专业咨询"}
{"query":"请比较哈希表和快速排序的区别。（含复杂度分析）","label":"通用知识"}
{"query":"请比较正态分布和线性回归的区别。（通俗解释）","label":"通用知识"}
{"query":"如何优化图的最短路径的性能？","label":"通用知识"}
{"query":"大数据工程师是否提供项目实战与源码？","label":"专业咨询"}
{"query":"如何在Windows下调试闭包相关问题？（含示例代码）","label":"通用知识"}
{"query":"全栈工程师班是否提供面授或线上直播？","label":"专业咨询"}
{"query":"机器学习实战课程的大纲是什么？","label":"专业咨询"}
{"query":"测试工程师的退款与退费流程是怎样的？","label":"专业咨询"}
{"query":"请比较贪心算法和复利计算的区别。（请给出示例）","label":"通用知识"}
{"query":"如何用JavaScript实现图的最短路径？请给出示例代码。（含复杂度分析）","label":"通用知识"}
{"query":"前端开发是否提供项目实战与源码？（含就业保障）","label":"专业咨询"}
{"query":"如何在Postman中使用缓存穿透？（通俗解释）","label":"通用知识"}
{"query":"测试工程师课程的大纲是什么？（面向初中级学员）","label":"专业咨询"}
{"query":"如何用SQL实现HTTPS加密流程？请给出示例代码。（通俗解释）","label":"通用知识"}
{"query":"前端开发师资力量由谁组成？（是否有企业讲师）（企业内训咨询）","label":"专业咨询"}
{"query":"如何在Git中使用缓存穿透？（含复杂度分析）","label":"通用知识"}
{"query":"JAVA全栈培训学费是多少？（面向在职人员）","label":"专业咨询"}
{"query":"Python数据分析是否支持分期付款或企业团报优惠？（企业内训咨询）","label":"专业咨询"}
{"query":"前端开发培训学费是多少？","label":"专业咨询"}
{"query":"移动开发的上课时间和周期是怎样的？（企业内训咨询）","label":"专业咨询"}
{"query":"请比较信号量和单例模式的区别。（含示例代码）","label":"通用知识"}
{"query":"大数据工程师在广州有校区吗？（企业内训咨询）","label":"专业咨询"}
{"query":"请说明回溯算法的原理和应用。（通俗解释）","label":"通用知识"}
{"query":"解释什么是分布式事务并给出示例代码。","label":"通用知识"}
{"query":"前端开发是否提供面授或线上直播？（含就业保障）","label":"专业咨询"}
{"query":"给出一个缓存穿透的实际例子并分析。（含示例代码）","label":"通用知识"}
{"query":"如何用Java实现HTTPS加密流程？请给出示例代码。（含示例代码）","label":"通用知识"}
{"query":"JAVA全栈在重庆有校区吗？（面向初中级学员）","label":"专业咨询"}
{"query":"如何优化支持向量机的性能？（含示例代码）","label":"通用知识"}
{"query":"移动开发是否支持分期付款或企业团报优惠？（面向在职人员）","label":"专业咨询"}
{"query":"如何优化A*搜索算法的性能？（含示例代码）","label":"通用知识"}
{"query":"如何用Rust实现随机森林？请给出示例代码。（请给出示例）","label":"通用知识"}
{"query":"如何在Docker容器下调试Docker镜像构建相关问题？（通俗解释）","label":"通用知识"}
{"query":"解释什么是图的最短路径并给出示例代码。（请给出示例）","label":"通用知识"}
{"query":"请写出Java中正则表达式的最佳实践。（含示例代码）","label":"通用知识"}
{"query":"给出一个随机森林的实际例子并分析。（含复杂度分析）","label":"通用知识"}
{"query":"请写出C++中Docker镜像构建的最佳实践。（请给出示例）","label":"通用知识"}
{"query":"请说明逻辑回归的原理和应用。（含复杂度分析）","label":"通用知识"}
{"query":"产品经理速成是否提供面授或线上直播？","label":"专业咨询"}
{"query":"全栈工程师班是否提供项目实战与源码？","label":"专业咨询"}
{"query":"测试工程师的退款与退费流程是怎样的？（面向初中级学员）","label":"专业咨询"}
{"query":"测试工程师在重庆有校区吗？（含就业保障）","label":"专业咨询"}
{"query":"如何在Kubernetes集群下调试闭包相关问题？","label":"通用知识"}
{"query":"如何在Windows下调试决策树相关问题？（通俗解释）","label":"通用知识"}
{"query":"JAVA全栈课程的大纲是什么？（面向在职人员）","label":"专业咨询"}
{"query":"如何优化线性回归的性能？（含示例代码）","label":"通用知识"}
{"query":"大数据工程师是否支持分期付款或企业团报优惠？","label":"专业咨询"}
{"query":"如何在Docker容器下调试支持向量机相关问题？（请给出示例）","label":"通用知识"}
{"query":"解释什么是复数模与辐角并给出示例代码。（含复杂度分析）","label":"通用知识"}
{"query":"给出一个HTTPS加密流程的实际例子并分析。（通俗解释）","label":"通用知识"}
{"query":"请说明分布式事务的原理和应用。（请给出示例）","label":"通用知识"}
{"query":"什么是二分查找？请用通俗语言解释。（含示例代码）","label":"通用知识"}
{"query":"给出一个卷积神经网络的实际例子并分析。（请给出示例）","label":"通用知识"}
{"query":"云原生工程师在深圳有校区吗？（含就业保障）","label":"专业咨询"}
{"query":"如何用Python实现拓扑排序？请给出示例代码。（含示例代码）","label":"通用知识"}
{"query":"如何在Linux下调试快速排序相关问题？（请给出示例）","label":"通用知识"}
{"query":"AI工程师实战班是否支持分期付款或企业团报优惠？（企业内训咨询）","label":"专业咨询"}
{"query":"JAVA全栈是否提供项目实战与源码？（面向初中级学员）","label":"专业咨询"}
{"query":"Python数据分析在杭州有校区吗？（面向在职人员）","label":"专业咨询"}
{"query":"产品经理速成有无就业推荐与岗前辅导？","label":"专业咨询"}
{"query":"机器学习实战师资力量由谁组成？（是否有企业讲师）（面向在职人员）","label":"专业咨询"}
{"query":"如何用Go实现动态规划？请给出示例代码。","label":"通用知识"}
{"query":"如何在VSCode中使用支持向量机？（请给出示例）","label":"通用知识"}
{"query":"请比较信息熵和拓扑排序的区别。","label":"通用知识"}
{"query":"什么是贪心算法？请用通俗语言解释。（含示例代码）","label":"通用知识"}
{"query":"如何在MacOS下调试虚拟内存相关问题？（通俗解释）","label":"通用知识"}
{"query":"AI工程师实战班是否提供面授或线上直播？","label":"专业咨询"}
{"query":"请比较动态规划和消息队列原理的区别。","label":"通用知识"}
{"query":"AI工程师实战班在成都有校区吗？（面向初中级学员）","label":"专业咨询"}
{"query":"机器学习实战是否支持分期付款或企业团报优惠？（企业内训咨询）","label":"专业咨询"}
{"query":"解释什么是逻辑回归并给出示例代码。（含示例代码）","label":"通用知识"}
{"query":"如何在Kubernetes集群下调试正则表达式的贪婪匹配相关问题？","label":"通用知识"}
{"query":"如何在Git中使用消息队列原理？（通俗解释）","label":"通用知识"}
{"query":"云原生工程师是否提供项目实战与源码？","label":"专业咨询"}
{"query":"如何在MacOS下调试RMSE和MAE相关问题？","label":"通用知识"}
{"query":"如何优化信息熵的性能？（含示例代码）","label":"通用知识"}
{"query":"前端开发培训学费是多少？（含就业保障）","label":"专业咨询"}
{"query":"Python数据分析是否支持分期付款或企业团报优惠？（面向初中级学员）","label":"专业咨询"}
{"query":"测试工程师课程的大纲是什么？（企业内训咨询）","label":"专业咨询"}
{"query":"请比较逻辑回归和特征工程的区别。","label":"通用知识"}
{"query":"AI工程师实战班的上课时间和周期是怎样的？（面向在职人员）","label":"专业咨询"}
{"query":"什么是复数模与辐角？请用通俗语言解释。（含复杂度分析）","label":"通用知识"}
{"query":"全栈工程师班课程的大纲是什么？（企业内训咨询）","label":"专业咨询"}
{"query":"大数据工程师是否提供项目实战与源码？（企业内训咨询）","label":"专业咨询"}
{"query":"请写出SQL中哈希表的最佳实践。（含复杂度分析）","label":"通用知识"}
{"query":"如何在Git中使用贝叶斯定理？（含示例代码）","label":"通用知识"}
{"query":"什么是信号量？请用通俗语言解释。（通俗解释）","label":"通用知识"}
{"query":"如何在Docker容器下调试缓存穿透相关问题？（请给出示例）","label":"通用知识"}
{"query":"测试工程师培训学费是多少？（面向初中级学员）","label":"专业咨询"}
{"query":"如何用Python实现图的最短路径？请给出示例代码。","label":"通用知识"}
{"query":"Python数据分析的上课时间和周期是怎样的？（面向初中级学员）","label":"专业咨询"}
{"query":"JAVA全栈培训学费是多少？（面向初中级学员）","label":"专业咨询"}
{"query":"数据库与运维有无就业推荐与岗前辅导？（含就业保障）","label":"专业咨询"}
{"query":"请说明正则表达式的贪婪匹配的原理和应用。（通俗解释）","label":"通用知识"}
{"query":"大数据工程师师资力量由谁组成？（是否有企业讲师）（面向初中级学员）","label":"专业咨询"}
{"query":"机器学习实战是否提供面授或线上直播？","label":"专业咨询"}
{"query":"如何优化分布式事务的性能？","label":"通用知识"}
{"query":"移动开发在重庆有校区吗？（面向初中级学员）","label":"专业咨询"}
{"query":"数据库与运维师资力量由谁组成？（是否有企业讲师）","label":"专业咨询"}
{"query":"如何在Windows下调试正则表达式的贪婪匹配相关问题？（含复杂度分析）","label":"通用知识"}
{"query":"请比较复数模与辐角和复利计算的区别。","label":"通用知识"}
{"query":"如何优化回溯算法的性能？（含复杂度分析）","label":"通用知识"}
{"query":"请说明复利计算的原理和应用。（通俗解释）","label":"通用知识"}
{"query":"请说明互斥锁的原理和应用。（含复杂度分析）","label":"通用知识"}
{"query":"前端开发课程的大纲是什么？（面向初中级学员）","label":"专业咨询"}
{"query":"移动开发是否提供项目实战与源码？（面向初中级学员）","label":"专业咨询"}
{"query":"什么是线性回归？请用通俗语言解释。（通俗解释）","label":"通用知识"}
{"query":"测试工程师是否支持分期付款或企业团报优惠？（含就业保障）","label":"专业咨询"}
{"query":"如何在Postman中使用矩阵求逆？（通俗解释）","label":"通用知识"}
{"query":"给出一个正则表达式的实际例子并分析。（通俗解释）","label":"通用知识"}
{"query":"如何在Linux下调试闭包相关问题？（含示例代码）","label":"通用知识"}
{"query":"AI工程师实战班师资力量由谁组成？（是否有企业讲师）（面向在职人员）","label":"专业咨询"}
{"query":"请比较特征工程和二分查找的区别。（含复杂度分析）","label":"通用知识"}
{"query":"机器学习实战有无就业推荐与岗前辅导？（面向初中级学员）","label":"专业咨询"}
{"query":"机器学习实战师资力量由谁组成？（是否有企业讲师）","label":"专业咨询"}
{"query":"大数据工程师是否支持分期付款或企业团报优惠？（含就业保障）","label":"专业咨询"}
{"query":"解释什么是贝叶斯定理并给出示例代码。（请给出示例）","label":"通用知识"}
{"query":"移动开发师资力量由谁组成？（是否有企业讲师）（面向初中级学员）","label":"专业咨询"}
{"query":"全栈工程师班的退款与退费流程是怎样的？（面向初中级学员）","label":"专业咨询"}
{"query":"产品经理速成在苏州有校区吗？（面向在职人员）","label":"专业咨询"}
{"query":"JAVA全栈的上课时间和周期是怎样的？（含就业保障）","label":"专业咨询"}
{"query":"如何用C++实现RPC原理？请给出示例代码。（请给出示例）","label":"通用知识"}
{"query":"移动开发课程的大纲是什么？（含就业保障）","label":"专业咨询"}
{"query":"如何用Go实现贪心算法？请给出示例代码。（含复杂度分析）","label":"通用知识"}
{"query":"JAVA全栈师资力量由谁组成？（是否有企业讲师）","label":"专业咨询"}
{"query":"移动开发在南京有校区吗？（企业内训咨询）","label":"专业咨询"}
{"query":"机器学习实战是否提供项目实战与源码？（面向初中级学员）","label":"专业咨询"}
{"query":"测试工程师是否支持分期付款或企业团报优惠？","label":"专业咨询"}
{"query":"产品经理速成的上课时间和周期是怎样的？（面向在职人员）","label":"专业咨询"}
{"query":"移动开发的退款与退费流程是怎样的？","label":"专业咨询"}
{"query":"什么是贪心算法？请用通俗语言解释。（请给出示例）","label":"通用知识"}
{"query":"给出一个矩阵求逆的实际例子并分析。（含示例代码）","label":"通用知识"}
{"query":"什么是动态规划？请用通俗语言解释。（通俗解释）","label":"通用知识"}
{"query":"JAVA全栈是否提供面授或线上直播？（企业内训咨询）","label":"专业咨询"}
{"query":"如何用Java实现K-means聚类？请给出示例代码。（通俗解释）","label":"通用知识"}
{"query":"AI工程师实战班的上课时间和周期是怎样的？（面向初中级学员）","label":"专业咨询"}
{"query":"机器学习实战课程的大纲是什么？（企业内训咨询）","label":"专业咨询"}
{"query":"前端开发是否提供面授或线上直播？（面向初中级学员）","label":"专业咨询"}
{"query":"云原生工程师师资力量由谁组成？（是否有企业讲师）（面向初中级学员）","label":"专业咨询"}
{"query":"Python数据分析师资力量由谁组成？（是否有企业讲师）（面向初中级学员）","label":"专业咨询"}
{"query":"什么是反向传播？请用通俗语言解释。（请给出示例）","label":"通用知识"}
{"query":"大数据工程师培训学费是多少？（含就业保障）","label":"专业咨询"}
{"query":"数据库与运维师资力量由谁组成？（是否有企业讲师）（含就业保障）","label":"专业咨询"}
{"query":"请说明反向传播的原理和应用。（请给出示例）","label":"通用知识"}
{"query":"AI工程师实战班是否提供项目实战与源码？","label":"专业咨询"}
{"query":"产品经理速成有无就业推荐与岗前辅导？（面向在职人员）","label":"专业咨询"}
{"query":"给出一个RPC原理的实际例子并分析。（通俗解释）","label":"通用知识"}
{"query":"机器学习实战是否支持分期付款或企业团报优惠？","label":"专业咨询"}
{"query":"全栈工程师班是否提供项目实战与源码？（企业内训咨询）","label":"专业咨询"}
{"query":"产品经理速成有无就业推荐与岗前辅导？（面向初中级学员）","label":"专业咨询"}
{"query":"给出一个线程同步的实际例子并分析。（请给出示例）","label":"通用知识"}
{"query":"如何在Redis中使用支持向量机？（含复杂度分析）","label":"通用知识"}
{"query":"给出一个闭包的实际例子并分析。（请给出示例）","label":"通用知识"}
{"query":"全栈工程师班的上课时间和周期是怎样的？（面向在职人员）","label":"专业咨询"}
{"query":"如何在Docker容器下调试梯度下降相关问题？（请给出示例）","label":"通用知识"}
{"query":"如何用Java实现闭包？请给出示例代码。（通俗解释）","label":"通用知识"}
{"query":"请比较线性回归和二分查找的区别。（请给出示例）","label":"通用知识"}
{"query":"测试工程师是否支持分期付款或企业团报优惠？（企业内训咨询）","label":"专业咨询"}
{"query":"前端开发课程的大纲是什么？（企业内训咨询）","label":"专业咨询"}
{"query":"数据库与运维在成都有校区吗？（面向在职人员）","label":"专业咨询"}
{"query":"前端开发培训学费是多少？（面向在职人员）","label":"专业咨询"}
{"query":"如何在Windows下调试复利计算相关问题？（含示例代码）","label":"通用知识"}
{"query":"如何在Postman中使用二分查找？（请给出示例）","label":"通用知识"}
{"query":"请说明矩阵求逆的原理和应用。（请给出示例）","label":"通用知识"}
{"query":"JAVA全栈在北京有校区吗？","label":"专业咨询"}
{"query":"移动开发的退款与退费流程是怎样的？（面向初中级学员）","label":"专业咨询"}
{"query":"Python数据分析有无就业推荐与岗前辅导？（面向初中级学员）","label":"专业咨询"}
{"query":"数据库与运维培训学费是多少？（面向初中级学员）","label":"专业咨询"}
{"query":"AI工程师实战班在重庆有校区吗？（面向在职人员）","label":"专业咨询"}
{"query":"JAVA全栈有无就业推荐与岗前辅导？（含就业保障）","label":"专业咨询"}
{"query":"什么是闭包？请用通俗语言解释。（通俗解释）","label":"通用知识"}
{"query":"Python数据分析是否提供面授或线上直播？（面向初中级学员）","label":"专业咨询"}
{"query":"请写出SQL中逻辑回归的最佳实践。（请给出示例）","label":"通用知识"}
{"query":"全栈工程师班课程的大纲是什么？（含就业保障）","label":"专业咨询"}
{"query":"数据库与运维在广州有校区吗？（面向初中级学员）","label":"专业咨询"}
{"query":"什么是缓存穿透？请用通俗语言解释。（通俗解释）","label":"通用知识"}
{"query":"如何在PyCharm中使用信号量？（通俗解释）","label":"通用知识"}
{"query":"Python数据分析培训学费是多少？（面向在职人员）","label":"专业咨询"}
{"query":"测试工程师有无就业推荐与岗前辅导？（含就业保障）","label":"专业咨询"}
{"query":"产品经理速成培训学费是多少？（面向初中级学员）","label":"专业咨询"}
{"query":"如何用SQL实现贝叶斯定理？请给出示例代码。（通俗解释）","label":"通用知识"}
{"query":"测试工程师是否提供项目实战与源码？（面向在职人员）","label":"专业咨询"}
{"query":"数据库与运维培训学费是多少？（企业内训咨询）","label":"专业咨询"}
{"query":"测试工程师师资力量由谁组成？（是否有企业讲师）（含就业保障）","label":"专业咨询"}
{"query":"大数据工程师培训学费是多少？（面向初中级学员）","label":"专业咨询"}
{"query":"如何用Bash实现线程同步？请给出示例代码。（含示例代码）","label":"通用知识"}
{"query":"数据库与运维的上课时间和周期是怎样的？（企业内训咨询）","label":"专业咨询"}
{"query":"如何用Python实现复利计算？请给出示例代码。（含复杂度分析）","label":"通用知识"}
{"query":"测试工程师师资力量由谁组成？（是否有企业讲师）（面向在职人员）","label":"专业咨询"}
{"query":"前端开发是否支持分期付款或企业团报优惠？","label":"专业咨询"}
{"query":"如何用JavaScript实现快速排序？请给出示例代码。","label":"通用知识"}
{"query":"产品经理速成的上课时间和周期是怎样的？（企业内训咨询）","label":"专业咨询"}
{"query":"请写出Java中HTTPS加密流程的最佳实践。（请给出示例）","label":"通用知识"}
{"query":"如何在Kubernetes集群下调试卷积神经网络相关问题？（通俗解释）","label":"通用知识"}
{"query":"请写出Rust中贪心算法的最佳实践。（含示例代码）","label":"通用知识"}
{"query":"前端开发是否支持分期付款或企业团报优惠？（面向在职人员）","label":"专业咨询"}
{"query":"请说明哈希表的原理和应用。（请给出示例）","label":"通用知识"}
{"query":"云原生工程师课程的大纲是什么？（含就业保障）","label":"专业咨询"}
{"query":"如何用SQL实现反向传播？请给出示例代码。","label":"通用知识"}
{"query":"如何优化A*搜索算法的性能？（通俗解释）","label":"通用知识"}
{"query":"全栈工程师班有无就业推荐与岗前辅导？（面向初中级学员）","label":"专业咨询"}
{"query":"如何在Windows下调试闭包相关问题？（含复杂度分析）","label":"通用知识"}
{"query":"如何用SQL实现闭包？请给出示例代码。","label":"通用知识"}
{"query":"如何用C++实现线性回归？请给出示例代码。（请给出示例）","label":"通用知识"}
{"query":"AI工程师实战班的退款与退费流程是怎样的？","label":"专业咨询"}
{"query":"数据库与运维是否提供项目实战与源码？（含就业保障）","label":"专业咨询"}
{"query":"如何在MacOS下调试Lambda表达式相关问题？（通俗解释）","label":"通用知识"}
{"query":"前端开发的退款与退费流程是怎样的？（面向在职人员）","label":"专业咨询"}
{"query":"如何在PyCharm中使用矩阵求逆？","label":"通用知识"}
{"query":"解释什么是OAuth认证并给出示例代码。（含示例代码）","label":"通用知识"}
{"query":"给出一个快速排序的实际例子并分析。（通俗解释）","label":"通用知识"}
{"query":"全栈工程师班在上海有校区吗？（面向在职人员）","label":"专业咨询"}
{"query":"云原生工程师是否提供面授或线上直播？（含就业保障）","label":"专业咨询"}
{"query":"产品经理速成课程的大纲是什么？（面向在职人员）","label":"专业咨询"}
{"query":"Python数据分析课程的大纲是什么？（面向在职人员）","label":"专业咨询"}
{"query":"请写出SQL中Kubernetes部署的最佳实践。（含复杂度分析）","label":"通用知识"}
{"query":"大数据工程师是否提供项目实战与源码？（含就业保障）","label":"专业咨询"}
{"query":"AI工程师实战班在南京有校区吗？（含就业保障）","label":"专业咨询"}
{"query":"如何优化正则表达式的贪婪匹配的性能？（含复杂度分析）","label":"通用知识"}
{"query":"机器学习实战的退款与退费流程是怎样的？（面向初中级学员）","label":"专业咨询"}
{"query":"云原生工程师有无就业推荐与岗前辅导？（面向初中级学员）","label":"专业咨询"}
{"query":"大数据工程师是否提供项目实战与源码？（面向在职人员）","label":"专业咨询"}
{"query":"云原生工程师的上课时间和周期是怎样的？（企业内训咨询）","label":"专业咨询"}
{"query":"如何在Windows下调试HTTPS加密流程相关问题？（通俗解释）","label":"通用知识"}
{"query":"移动开发是否提供项目实战与源码？（含就业保障）","label":"专业咨询"}
{"query":"产品经理速成是否支持分期付款或企业团报优惠？（面向在职人员）","label":"专业咨询"}
{"query":"测试工程师在重庆有校区吗？（面向初中级学员）","label":"专业咨询"}
{"query":"给出一个哈希表的实际例子并分析。","label":"通用知识"}
{"query":"AI工程师实战班是否提供面授或线上直播？（企业内训咨询）","label":"专业咨询"}
{"query":"请写出SQL中消息队列原理的最佳实践。（请给出示例）","label":"通用知识"}
{"query":"测试工程师的上课时间和周期是怎样的？","label":"专业咨询"}
{"query":"给出一个Lambda表达式的实际例子并分析。（通俗解释）","label":"通用知识"}
{"query":"云原生工程师的上课时间和周期是怎样的？（面向初中级学员）","label":"专业咨询"}
{"query":"AI工程师实战班是否提供面授或线上直播？（面向初中级学员）","label":"专业咨询"}
{"query":"AI工程师实战班在武汉有校区吗？（面向初中级学员）","label":"专业咨询"}
{"query":"机器学习实战是否提供项目实战与源码？（企业内训咨询）","label":"专业咨询"}
{"query":"解释什么是RMSE和MAE并给出示例代码。（通俗解释）","label":"通用知识"}
{"query":"什么是互斥锁？请用通俗语言解释。（含复杂度分析）","label":"通用知识"}
{"query":"请说明HTTPS加密流程的原理和应用。（含示例代码）","label":"通用知识"}
{"query":"移动开发是否提供项目实战与源码？","label":"专业咨询"}
{"query":"如何在Windows下调试随机森林相关问题？","label":"通用知识"}
{"query":"机器学习实战师资力量由谁组成？（是否有企业讲师）（企业内训咨询）","label":"专业咨询"}
{"query":"产品经理速成师资力量由谁组成？（是否有企业讲师）","label":"专业咨询"}
{"query":"前端开发是否支持分期付款或企业团报优惠？（面向初中级学员）","label":"专业咨询"}
{"query":"解释什么是快速排序并给出示例代码。（请给出示例）","label":"通用知识"}
{"query":"AI工程师实战班有无就业推荐与岗前辅导？（含就业保障）","label":"专业咨询"}
{"query":"解释什么是Docker镜像构建并给出示例代码。（请给出示例）","label":"通用知识"}
{"query":"前端开发有无就业推荐与岗前辅导？（面向初中级学员）","label":"专业咨询"}
{"query":"前端开发的退款与退费流程是怎样的？（面向初中级学员）","label":"专业咨询"}
{"query":"解释什么是正则表达式并给出示例代码。（含示例代码）","label":"通用知识"}
{"query":"如何在Postman中使用单例模式？（通俗解释）","label":"通用知识"}
{"query":"AI工程师实战班师资力量由谁组成？（是否有企业讲师）（企业内训咨询）","label":"专业咨询"}
{"query":"什么是复利计算？请用通俗语言解释。","label":"通用知识"}
{"query":"请写出JavaScript中RMSE和MAE的最佳实践。（请给出示例）","label":"通用知识"}
{"query":"产品经理速成是否支持分期付款或企业团报优惠？（面向初中级学员）","label":"专业咨询"}
{"query":"Python数据分析的上课时间和周期是怎样的？（含就业保障）","label":"专业咨询"}
{"query":"如何用Go实现A*搜索算法？请给出示例代码。（请给出示例）","label":"通用知识"}
{"query":"云原生工程师师资力量由谁组成？（是否有企业讲师）","label":"专业咨询"}
{"query":"给出一个动态规划的实际例子并分析。（含示例代码）","label":"通用知识"}
{"query":"JAVA全栈是否提供项目实战与源码？（企业内训咨询）","label":"专业咨询"}
{"query":"移动开发师资力量由谁组成？（是否有企业讲师）（企业内训咨询）","label":"专业咨询"}
{"query":"产品经理速成是否提供面授或线上直播？（面向初中级学员）","label":"专业咨询"}
{"query":"如何在Windows下调试Kubernetes部署相关问题？（含示例代码）","label":"通用知识"}
{"query":"移动开发在南京有校区吗？（面向在职人员）","label":"专业咨询"}
{"query":"如何用Rust实现缓存穿透？请给出示例代码。（请给出示例）","label":"通用知识"}
{"query":"全栈工程师班师资力量由谁组成？（是否有企业讲师）（面向初中级学员）","label":"专业咨询"}
{"query":"JAVA全栈培训学费是多少？","label":"专业咨询"}
{"query":"测试工程师是否提供面授或线上直播？（企业内训咨询）","label":"专业咨询"}
{"query":"产品经理速成师资力量由谁组成？（是否有企业讲师）（面向在职人员）","label":"专业咨询"}
{"query":"请说明OAuth认证的原理和应用。","label":"通用知识"}
{"query":"产品经理速成培训学费是多少？（面向在职人员）","label":"专业咨询"}
{"query":"数据库与运维是否提供项目实战与源码？（面向在职人员）","label":"专业咨询"}
{"query":"AI工程师实战班有无就业推荐与岗前辅导？（企业内训咨询）","label":"专业咨询"}
{"query":"给出一个RPC原理的实际例子并分析。（含示例代码）","label":"通用知识"}
{"query":"全栈工程师班的退款与退费流程是怎样的？（含就业保障）","label":"专业咨询"}
{"query":"如何优化哈希表的性能？（通俗解释）","label":"通用知识"}
{"query":"请比较Kubernetes部署和A*搜索算法的区别。（含示例代码）","label":"通用知识"}
{"query":"请写出Python中混淆矩阵的最佳实践。（含复杂度分析）","label":"通用知识"}
{"query":"移动开发的退款与退费流程是怎样的？（面向在职人员）","label":"专业咨询"}
{"query":"什么是二分查找？请用通俗语言解释。（通俗解释）","label":"通用知识"}
{"query":"给出一个支持向量机的实际例子并分析。（通俗解释）","label":"通用知识"}
{"query":"解释什么是A*搜索算法并给出示例代码。（通俗解释）","label":"通用知识"}
{"query":"如何在Postman中使用二叉树遍历？（含复杂度分析）","label":"通用知识"}
{"query":"云原生工程师培训学费是多少？（面向初中级学员）","label":"专业咨询"}
{"query":"如何在PyCharm中使用正则表达式的贪婪匹配？（通俗解释）","label":"通用知识"}
{"query":"云原生工程师的上课时间和周期是怎样的？（含就业保障）","label":"专业咨询"}
{"query":"什么是Lambda表达式？请用通俗语言解释。（含示例代码）","label":"通用知识"}
{"query":"给出一个信息熵的实际例子并分析。（通俗解释）","label":"通用知识"}
{"query":"请说明Kubernetes部署的原理和应用。","label":"通用知识"}
{"query":"产品经理速成是否提供项目实战与源码？（面向初中级学员）","label":"专业咨询"}
{"query":"给出一个逻辑回归的实际例子并分析。（含复杂度分析）","label":"通用知识"}
{"query":"请比较HTTPS加密流程和卷积神经网络的区别。（通俗解释）","label":"通用知识"}
{"query":"测试工程师课程的大纲是什么？（面向在职人员）","label":"专业咨询"}
{"query":"请写出Rust中归并排序的最佳实践。","label":"通用知识"}
{"query":"前端开发师资力量由谁组成？（是否有企业讲师）（含就业保障）","label":"专业咨询"}
{"query":"解释什么是互斥锁并给出示例代码。（含复杂度分析）","label":"通用知识"}
{"query":"前端开发有无就业推荐与岗前辅导？","label":"专业咨询"}
{"query":"如何用Java实现动态规划？请给出示例代码。（含复杂度分析）","label":"通用知识"}
{"query":"如何优化卷积神经网络的性能？","label":"通用知识"}
{"query":"给出一个复数模与辐角的实际例子并分析。（请给出示例）","label":"通用知识"}
{"query":"数据库与运维是否提供项目实战与源码？（面向初中级学员）","label":"专业咨询"}
{"query":"前端开发的退款与退费流程是怎样的？（含就业保障）","label":"专业咨询"}
{"query":"如何用SQL实现复数模与辐角？请给出示例代码。（含示例代码）","label":"通用知识"}
{"query":"机器学习实战培训学费是多少？（企业内训咨询）","label":"专业咨询"}
{"query":"什么是复利计算？请用通俗语言解释。（含示例代码）","label":"通用知识"}
{"query":"请说明正则表达式的贪婪匹配的原理和应用。（请给出示例）","label":"通用知识"}
{"query":"如何在Windows下调试信息熵相关问题？（请给出示例）","label":"通用知识"}
{"query":"请比较PCA主成分分析和拓扑排序的区别。（通俗解释）","label":"通用知识"}
{"query":"AI工程师实战班课程的大纲是什么？（含就业保障）","label":"专业咨询"}
{"query":"移动开发的上课时间和周期是怎样的？","label":"专业咨询"}
{"query":"如何优化特征工程的性能？（含复杂度分析）","label":"通用知识"}
{"query":"大数据工程师是否提供面授或线上直播？（企业内训咨询）","label":"专业咨询"}
{"query":"请写出C++中二分查找的最佳实践。（含复杂度分析）","label":"通用知识"}
{"query":"如何在Git中使用快速排序？（含复杂度分析）","label":"通用知识"}
{"query":"云原生工程师是否支持分期付款或企业团报优惠？（面向初中级学员）","label":"专业咨询"}
{"query":"如何用Python实现Kubernetes部署？请给出示例代码。（请给出示例）","label":"通用知识"}
{"query":"产品经理速成的退款与退费流程是怎样的？（企业内训咨询）","label":"专业咨询"}
{"query":"大数据工程师有无就业推荐与岗前辅导？（面向初中级学员）","label":"专业咨询"}
{"query":"如何在Redis中使用RMSE和MAE？（请给出示例）","label":"通用知识"}
{"query":"产品经理速成培训学费是多少？","label":"专业咨询"}
{"query":"给出一个RPC原理的实际例子并分析。（含复杂度分析）","label":"通用知识"}
{"query":"如何用Python实现正则表达式的贪婪匹配？请给出示例代码。（含复杂度分析）","label":"通用知识"}
{"query":"AI工程师实战班课程的大纲是什么？","label":"专业咨询"}
{"query":"云原生工程师是否支持分期付款或企业团报优惠？（面向在职人员）","label":"专业咨询"}
{"query":"如何优化复利计算的性能？（含复杂度分析）","label":"通用知识"}
{"query":"给出一个逻辑回归的实际例子并分析。（请给出示例）","label":"通用知识"}
{"query":"数据库与运维培训学费是多少？","label":"专业咨询"}
{"query":"给出一个Lambda表达式的实际例子并分析。（请给出示例）","label":"通用知识"}
{"query":"如何优化动态规划的性能？（含复杂度分析）","label":"通用知识"}
{"query":"如何优化贝叶斯定理的性能？（含示例代码）","label":"通用知识"}
{"query":"请写出C++中图的最短路径的最佳实践。（请给出示例）","label":"通用知识"}
{"query":"解释什么是回溯算法并给出示例代码。","label":"通用知识"}
{"query":"如何优化正态分布的性能？（通俗解释）","label":"通用知识"}
{"query":"JAVA全栈师资力量由谁组成？（是否有企业讲师）（面向初中级学员）","label":"专业咨询"}
{"query":"解释什么是虚拟内存并给出示例代码。（含复杂度分析）","label":"通用知识"}
{"query":"Python数据分析培训学费是多少？（面向初中级学员）","label":"专业咨询"}
{"query":"前端开发在南京有校区吗？（面向在职人员）","label":"专业咨询"}
{"query":"解释什么是TCP三次握手并给出示例代码。（含示例代码）","label":"通用知识"}
{"query":"如何在Windows下调试A*搜索算法相关问题？（请给出示例）","label":"通用知识"}
{"query":"如何优化Docker镜像构建的性能？（含复杂度分析）","label":"通用知识"}
{"query":"测试工程师的退款与退费流程是怎样的？（企业内训咨询）","label":"专业咨询"}
{"query":"请写出Rust中互斥锁的最佳实践。（请给出示例）","label":"通用知识"}
{"query":"AI工程师实战班的上课时间和周期是怎样的？（企业内训咨询）","label":"专业咨询"}
{"query":"如何优化RPC原理的性能？（通俗解释）","label":"通用知识"}
{"query":"请比较复利计算和复数模与辐角的区别。","label":"通用知识"}
{"query":"如何优化贝叶斯定理的性能？（含复杂度分析）","label":"通用知识"}
{"query":"如何优化二叉树遍历的性能？","label":"通用知识"}
{"query":"AI工程师实战班培训学费是多少？","label":"专业咨询"}
{"query":"JAVA全栈的上课时间和周期是怎样的？（面向在职人员）","label":"专业咨询"}
{"query":"请比较RESTful API和信息熵的区别。（含复杂度分析）","label":"通用知识"}
{"query":"请比较OAuth认证和虚拟内存的区别。","label":"通用知识"}
{"query":"解释什么是归并排序并给出示例代码。（含复杂度分析）","label":"通用知识"}
{"query":"什么是正则表达式的贪婪匹配？请用通俗语言解释。（请给出示例）","label":"通用知识"}
{"query":"JAVA全栈在成都有校区吗？（面向在职人员）","label":"专业咨询"}
{"query":"如何在Jenkins中使用Lambda表达式？（通俗解释）","label":"通用知识"}
{"query":"如何在Docker容器下调试混淆矩阵相关问题？（请给出示例）","label":"通用知识"}
{"query":"如何在Redis中使用二叉树遍历？（含复杂度分析）","label":"通用知识"}
{"query":"解释什么是正则表达式的贪婪匹配并给出示例代码。（含复杂度分析）","label":"通用知识"}
{"query":"Python数据分析在南京有校区吗？","label":"专业咨询"}
{"query":"产品经理速成是否支持分期付款或企业团报优惠？（含就业保障）","label":"专业咨询"}
{"query":"如何优化PCA主成分分析的性能？（含示例代码）","label":"通用知识"}
{"query":"数据库与运维的上课时间和周期是怎样的？","label":"专业咨询"}
{"query":"如何优化Lambda表达式的性能？（含示例代码）","label":"通用知识"}
{"query":"前端开发的退款与退费流程是怎样的？","label":"专业咨询"}
{"query":"什么是拓扑排序？请用通俗语言解释。（含示例代码）","label":"通用知识"}
{"query":"大数据工程师课程的大纲是什么？（企业内训咨询）","label":"专业咨询"}
{"query":"请写出Python中虚拟内存的最佳实践。（通俗解释）","label":"通用知识"}
{"query":"前端开发师资力量由谁组成？（是否有企业讲师）（面向在职人员）","label":"专业咨询"}
{"query":"请写出Rust中卷积神经网络的最佳实践。（含示例代码）","label":"通用知识"}
{"query":"如何在Docker中使用图的最短路径？（含示例代码）","label":"通用知识"}
{"query":"全栈工程师班在武汉有校区吗？（含就业保障）","label":"专业咨询"}
{"query":"什么是梯度下降？请用通俗语言解释。（请给出示例）","label":"通用知识"}
{"query":"如何在Postman中使用HTTPS加密流程？","label":"通用知识"}
{"query":"请写出SQL中信号量的最佳实践。（请给出示例）","label":"通用知识"}
{"query":"如何在Git中使用动态规划？（请给出示例）","label":"通用知识"}
{"query":"数据库与运维在上海有校区吗？","label":"专业咨询"}
{"query":"Python数据分析的上课时间和周期是怎样的？","label":"专业咨询"}
{"query":"如何用Bash实现混淆矩阵？请给出示例代码。（请给出示例）","label":"通用知识"}
{"query":"数据库与运维的上课时间和周期是怎样的？（含就业保障）","label":"专业咨询"}
{"query":"AI工程师实战班师资力量由谁组成？（是否有企业讲师）（面向初中级学员）","label":"专业咨询"}
{"query":"测试工程师是否提供面授或线上直播？（含就业保障）","label":"专业咨询"}
{"query":"移动开发有无就业推荐与岗前辅导？（含就业保障）","label":"专业咨询"}
{"query":"Python数据分析有无就业推荐与岗前辅导？","label":"专业咨询"}
{"query":"移动开发在南京有校区吗？（含就业保障）","label":"专业咨询"}
{"query":"如何在Windows下调试K-means聚类相关问题？（含示例代码）","label":"通用知识"}
{"query":"如何在Kubernetes集群下调试RMSE和MAE相关问题？（含示例代码）","label":"通用知识"}
{"query":"如何优化Lambda表达式的性能？（通俗解释）","label":"通用知识"}
{"query":"机器学习实战培训学费是多少？（面向在职人员）","label":"专业咨询"}
{"query":"如何在MacOS下调试二叉树遍历相关问题？","label":"通用知识"}
{"query":"JAVA全栈在武汉有校区吗？","label":"专业咨询"}
{"query":"前端开发有无就业推荐与岗前辅导？（企业内训咨询）","label":"专业咨询"}
{"query":"请说明随机森林的原理和应用。（含复杂度分析）","label":"通用知识"}
{"query":"如何用JavaScript实现梯度下降？请给出示例代码。（含复杂度分析）","label":"通用知识"}
{"query":"给出一个缓存穿透的实际例子并分析。（通俗解释）","label":"通用知识"}
{"query":"如何在Jenkins中使用信号量？（含复杂度分析）","label":"通用知识"}
{"query":"前端开发在上海有校区吗？（面向在职人员）","label":"专业咨询"}
{"query":"如何用JavaScript实现消息队列原理？请给出示例代码。（含复杂度分析）","label":"通用知识"}
{"query":"请写出Rust中正态分布的最佳实践。（通俗解释）","label":"通用知识"}
{"query":"移动开发是否支持分期付款或企业团报优惠？","label":"专业咨询"}
{"query":"如何优化逻辑回归的性能？（含示例代码）","label":"通用知识"}
{"query":"如何在Kubernetes集群下调试复利计算相关问题？（通俗解释）","label":"通用知识"}
{"query":"AI工程师实战班是否提供项目实战与源码？（企业内训咨询）","label":"专业咨询"}
{"query":"产品经理速成师资力量由谁组成？（是否有企业讲师）（含就业保障）","label":"专业咨询"}
{"query":"如何在Docker中使用A*搜索算法？（通俗解释）","label":"通用知识"}
{"query":"大数据工程师的上课时间和周期是怎样的？（企业内训咨询）","label":"专业咨询"}
{"query":"如何用Rust实现快速排序？请给出示例代码。","label":"通用知识"}
{"query":"产品经理速成是否提供面授或线上直播？（含就业保障）","label":"专业咨询"}
{"query":"机器学习实战是否提供项目实战与源码？（面向在职人员）","label":"专业咨询"}
{"query":"如何在PyCharm中使用拓扑排序？（含示例代码）","label":"通用知识"}
{"query":"请说明正则表达式的原理和应用。（请给出示例）","label":"通用知识"}
{"query":"数据库与运维课程的大纲是什么？（面向初中级学员）","label":"专业咨询"}
{"query":"机器学习实战有无就业推荐与岗前辅导？（含就业保障）","label":"专业咨询"}
{"query":"AI工程师实战班是否提供项目实战与源码？（面向在职人员）","label":"专业咨询"}
{"query":"全栈工程师班培训学费是多少？（面向在职人员）","label":"专业咨询"}
{"query":"如何在Docker中使用逻辑回归？（请给出示例）","label":"通用知识"}
{"query":"AI工程师实战班在北京有校区吗？（含就业保障）","label":"专业咨询"}
{"query":"给出一个OAuth认证的实际例子并分析。（通俗解释）","label":"通用知识"}
{"query":"云原生工程师培训学费是多少？（企业内训咨询）","label":"专业咨询"}
{"query":"如何在Git中使用混淆矩阵？（通俗解释）","label":"通用知识"}
{"query":"请比较信号量和RESTful API的区别。（请给出示例）","label":"通用知识"}
{"query":"Python数据分析的上课时间和周期是怎样的？（面向在职人员）","label":"专业咨询"}
{"query":"给出一个快速排序的实际例子并分析。","label":"通用知识"}
{"query":"请写出Rust中RESTful API的最佳实践。（含复杂度分析）","label":"通用知识"}
{"query":"解释什么是二分查找并给出示例代码。（通俗解释）","label":"通用知识"}
{"query":"给出一个Kubernetes部署的实际例子并分析。（请给出示例）","label":"通用知识"}
{"query":"大数据工程师是否提供面授或线上直播？（面向初中级学员）","label":"专业咨询"}
{"query":"请说明信息熵的原理和应用。（含示例代码）","label":"通用知识"}
{"query":"请说明K折交叉验证的原理和应用。（通俗解释）","label":"通用知识"}
{"query":"请写出Go中RMSE和MAE的最佳实践。（请给出示例）","label":"通用知识"}
{"query":"移动开发是否支持分期付款或企业团报优惠？（面向初中级学员）","label":"专业咨询"}
{"query":"Python数据分析在重庆有校区吗？（企业内训咨询）","label":"专业咨询"}
{"query":"什么是LRU缓存？请用通俗语言解释。（含复杂度分析）","label":"通用知识"}
{"query":"前端开发的上课时间和周期是怎样的？（面向在职人员）","label":"专业咨询"}
{"query":"如何优化正则表达式的贪婪匹配的性能？（通俗解释）","label":"通用知识"}
{"query":"Python数据分析在杭州有校区吗？（含就业保障）","label":"专业咨询"}
{"query":"Python数据分析师资力量由谁组成？（是否有企业讲师）（面向在职人员）","label":"专业咨询"}
{"query":"云原生工程师在广州有校区吗？（面向在职人员）","label":"专业咨询"}
{"query":"如何在Linux下调试信号量相关问题？（含复杂度分析）","label":"通用知识"}
{"query":"如何优化单例模式的性能？（通俗解释）","label":"通用知识"}
{"query":"全栈工程师班是否提供面授或线上直播？（面向在职人员）","label":"专业咨询"}
{"query":"全栈工程师班在南京有校区吗？（面向初中级学员）","label":"专业咨询"}
{"query":"移动开发在深圳有校区吗？（面向初中级学员）","label":"专业咨询"}
{"query":"机器学习实战课程的大纲是什么？（面向在职人员）","label":"专业咨询"}
{"query":"产品经理速成的退款与退费流程是怎样的？（面向初中级学员）","label":"专业咨询"}
{"query":"测试工程师在南京有校区吗？（含就业保障）","label":"专业咨询"}
{"query":"什么是卷积神经网络？请用通俗语言解释。（通俗解释）","label":"通用知识"}
{"query":"云原生工程师是否提供面授或线上直播？","label":"专业咨询"}
{"query":"给出一个哈希表的实际例子并分析。（含示例代码）","label":"通用知识"}
{"query":"产品经理速成的上课时间和周期是怎样的？","label":"专业咨询"}
{"query":"大数据工程师课程的大纲是什么？（含就业保障）","label":"专业咨询"}
{"query":"产品经理速成有无就业推荐与岗前辅导？（企业内训咨询）","label":"专业咨询"}
{"query":"Python数据分析是否提供面授或线上直播？（企业内训咨询）","label":"专业咨询"}
{"query":"移动开发的上课时间和周期是怎样的？（面向在职人员）","label":"专业咨询"}
{"query":"机器学习实战的上课时间和周期是怎样的？（面向初中级学员）","label":"专业咨询"}
{"query":"如何用SQL实现LRU缓存？请给出示例代码。","label":"通用知识"}
{"query":"给出一个LRU缓存的实际例子并分析。（请给出示例）","label":"通用知识"}
{"query":"给出一个PCA主成分分析的实际例子并分析。（含复杂度分析）","label":"通用知识"}
{"query":"移动开发的上课时间和周期是怎样的？（含就业保障）","label":"专业咨询"}
{"query":"数据库与运维是否提供项目实战与源码？（企业内训咨询）","label":"专业咨询"}
{"query":"给出一个梯度下降的实际例子并分析。（请给出示例）","label":"通用知识"}
{"query":"机器学习实战的上课时间和周期是怎样的？（面向在职人员）","label":"专业咨询"}
{"query":"JAVA全栈在重庆有校区吗？（企业内训咨询）","label":"专业咨询"}
{"query":"解释什么是矩阵求逆并给出示例代码。（请给出示例）","label":"通用知识"}
{"query":"请比较单例模式和复数模与辐角的区别。","label":"通用知识"}
{"query":"前端开发在苏州有校区吗？（含就业保障）","label":"专业咨询"}
{"query":"产品经理速成培训学费是多少？（含就业保障）","label":"专业咨询"}
{"query":"产品经理速成在广州有校区吗？（面向初中级学员）","label":"专业咨询"}
{"query":"如何在Linux下调试正态分布相关问题？","label":"通用知识"}
{"query":"产品经理速成的退款与退费流程是怎样的？（含就业保障）","label":"专业咨询"}
{"query":"全栈工程师班有无就业推荐与岗前辅导？（含就业保障）","label":"专业咨询"}
{"query":"请比较特征工程和信号量的区别。（含复杂度分析）","label":"通用知识"}
{"query":"JAVA全栈是否提供面授或线上直播？（含就业保障）","label":"专业咨询"}
{"query":"数据库与运维是否支持分期付款或企业团报优惠？（含就业保障）","label":"专业咨询"}
{"query":"给出一个单例模式的实际例子并分析。","label":"通用知识"}
{"query":"前端开发培训学费是多少？（面向初中级学员）","label":"专业咨询"}
{"query":"数据库与运维是否提供面授或线上直播？","label":"专业咨询"}
{"query":"如何用Rust实现复利计算？请给出示例代码。（含示例代码）","label":"通用知识"}
{"query":"请写出Bash中贪心算法的最佳实践。（含示例代码）","label":"通用知识"}
{"query":"如何用Bash实现正态分布？请给出示例代码。（请给出示例）","label":"通用知识"}
{"query":"测试工程师是否提供面授或线上直播？","label":"专业咨询"}
{"query":"什么是复利计算？请用通俗语言解释。（含复杂度分析）","label":"通用知识"}
{"query":"什么是K折交叉验证？请用通俗语言解释。","label":"通用知识"}
{"query":"请写出Rust中线性回归的最佳实践。（请给出示例）","label":"通用知识"}
{"query":"请比较互斥锁和Docker镜像构建的区别。（含复杂度分析）","label":"通用知识"}
{"query":"给出一个归并排序的实际例子并分析。","label":"通用知识"}
{"query":"解释什么是RESTful API并给出示例代码。（通俗解释）","label":"通用知识"}
{"query":"移动开发是否提供面授或线上直播？","label":"专业咨询"}
{"query":"数据库与运维在深圳有校区吗？（面向初中级学员）","label":"专业咨询"}
{"query":"解释什么是复利计算并给出示例代码。（含示例代码）","label":"通用知识"}
{"query":"请写出C++中反向传播的最佳实践。（含复杂度分析）","label":"通用知识"}
{"query":"如何在Docker容器下调试Lambda表达式相关问题？（请给出示例）","label":"通用知识"}
{"query":"大数据工程师在北京有校区吗？（企业内训咨询）","label":"专业咨询"}
{"query":"给出一个正态分布的实际例子并分析。","label":"通用知识"}
{"query":"机器学习实战培训学费是多少？（含就业保障）","label":"专业咨询"}
{"query":"如何在MacOS下调试信号量相关问题？（请给出示例）","label":"通用知识"}
{"query":"如何在Windows下调试梯度下降相关问题？","label":"通用知识"}
{"query":"解释什么是卷积神经网络并给出示例代码。（通俗解释）","label":"通用知识"}
{"query":"云原生工程师在武汉有校区吗？（面向初中级学员）","label":"专业咨询"}
{"query":"大数据工程师是否支持分期付款或企业团报优惠？（面向初中级学员）","label":"专业咨询"}
{"query":"移动开发课程的大纲是什么？","label":"专业咨询"}
{"query":"什么是随机森林？请用通俗语言解释。（通俗解释）","label":"通用知识"}
{"query":"机器学习实战在南京有校区吗？（企业内训咨询）","label":"专业咨询"}
{"query":"请写出Rust中哈希表的最佳实践。（通俗解释）","label":"通用知识"}
{"query":"如何优化哈希表的性能？（含复杂度分析）","label":"通用知识"}
{"query":"解释什么是A*搜索算法并给出示例代码。（含示例代码）","label":"通用知识"}
{"query":"什么是LRU缓存？请用通俗语言解释。（请给出示例）","label":"通用知识"}
{"query":"Python数据分析是否提供项目实战与源码？（含就业保障）","label":"专业咨询"}
{"query":"全栈工程师班在深圳有校区吗？（面向在职人员）","label":"专业咨询"}
{"query":"如何在Docker容器下调试矩阵求逆相关问题？","label":"通用知识"}
{"query":"JAVA全栈有无就业推荐与岗前辅导？（企业内训咨询）","label":"专业咨询"}
{"query":"JAVA全栈在杭州有校区吗？（面向初中级学员）","label":"专业咨询"}
{"query":"产品经理速成是否支持分期付款或企业团报优惠？","label":"专业咨询"}
{"query":"解释什么是信息熵并给出示例代码。（请给出示例）","label":"通用知识"}
{"query":"请比较RESTful API和K折交叉验证的区别。（请给出示例）","label":"通用知识"}
{"query":"请写出SQL中HTTPS加密流程的最佳实践。（通俗解释）","label":"通用知识"}
{"query":"如何在Docker容器下调试梯度下降相关问题？（通俗解释）","label":"通用知识"}
{"query":"机器学习实战有无就业推荐与岗前辅导？（面向在职人员）","label":"专业咨询"}
{"query":"如何用JavaScript实现K折交叉验证？请给出示例代码。（含复杂度分析）","label":"通用知识"}
{"query":"请写出Rust中回溯算法的最佳实践。","label":"通用知识"}
{"query":"如何在Linux下调试Kubernetes部署相关问题？（含复杂度分析）","label":"通用知识"}
{"query":"全栈工程师班在南京有校区吗？（含就业保障）","label":"专业咨询"}
{"query":"大数据工程师师资力量由谁组成？（是否有企业讲师）（含就业保障）","label":"专业咨询"}
{"query":"测试工程师在北京有校区吗？（含就业保障）","label":"专业咨询"}
{"query":"移动开发师资力量由谁组成？（是否有企业讲师）（含就业保障）","label":"专业咨询"}
{"query":"如何在Redis中使用决策树？（含复杂度分析）","label":"通用知识"}
{"query":"大数据工程师的退款与退费流程是怎样的？","label":"专业咨询"}
{"query":"请说明卷积神经网络的原理和应用。","label":"通用知识"}
{"query":"如何用Go实现虚拟内存？请给出示例代码。（通俗解释）","label":"通用知识"}
{"query":"JAVA全栈是否支持分期付款或企业团报优惠？（企业内训咨询）","label":"专业咨询"}
{"query":"请比较HTTPS加密流程和缓存穿透的区别。","label":"通用知识"}
{"query":"如何在Docker容器下调试复数模与辐角相关问题？（请给出示例）","label":"通用知识"}
{"query":"什么是拓扑排序？请用通俗语言解释。","label":"通用知识"}
{"query":"请比较RPC原理和回溯算法的区别。（请给出示例）","label":"通用知识"}
{"query":"Python数据分析师资力量由谁组成？（是否有企业讲师）","label":"专业咨询"}
{"query":"Python数据分析的退款与退费流程是怎样的？（面向在职人员）","label":"专业咨询"}
{"query":"移动开发在重庆有校区吗？（企业内训咨询）","label":"专业咨询"}
{"query":"如何优化拓扑排序的性能？（请给出示例）","label":"通用知识"}
{"query":"请说明虚拟内存的原理和应用。（通俗解释）","label":"通用知识"}
{"query":"什么是Lambda表达式？请用通俗语言解释。（含复杂度分析）","label":"通用知识"}
{"query":"请说明RPC原理的原理和应用。（请给出示例）","label":"通用知识"}
{"query":"如何优化Kubernetes部署的性能？（请给出示例）","label":"通用知识"}
{"query":"JAVA全栈课程的大纲是什么？","label":"专业咨询"}
{"query":"产品经理速成课程的大纲是什么？（企业内训咨询）","label":"专业咨询"}
{"query":"请比较线程同步和PCA主成分分析的区别。（含示例代码）","label":"通用知识"}
{"query":"机器学习实战在北京有校区吗？（面向初中级学员）","label":"专业咨询"}
{"query":"前端开发的上课时间和周期是怎样的？","label":"专业咨询"}
{"query":"如何在MacOS下调试贝叶斯定理相关问题？（请给出示例）","label":"通用知识"}
{"query":"Python数据分析有无就业推荐与岗前辅导？（企业内训咨询）","label":"专业咨询"}
{"query":"请比较RMSE和MAE和互斥锁的区别。","label":"通用知识"}
{"query":"云原生工程师有无就业推荐与岗前辅导？（面向在职人员）","label":"专业咨询"}
{"query":"解释什么是矩阵求逆并给出示例代码。（通俗解释）","label":"通用知识"}
{"query":"全栈工程师班的退款与退费流程是怎样的？","label":"专业咨询"}
{"query":"如何在Linux下调试信号量相关问题？（请给出示例）","label":"通用知识"}
{"query":"请比较决策树和复数模与辐角的区别。（含复杂度分析）","label":"通用知识"}
{"query":"全栈工程师班课程的大纲是什么？（面向初中级学员）","label":"专业咨询"}
{"query":"什么是PCA主成分分析？请用通俗语言解释。（含示例代码）","label":"通用知识"}
{"query":"移动开发有无就业推荐与岗前辅导？","label":"专业咨询"}
{"query":"如何优化反向传播的性能？（请给出示例）","label":"通用知识"}
{"query":"解释什么是RMSE和MAE并给出示例代码。（含复杂度分析）","label":"通用知识"}
{"query":"Python数据分析是否提供项目实战与源码？（企业内训咨询）","label":"专业咨询"}
{"query":"JAVA全栈是否提供面授或线上直播？","label":"专业咨询"}
{"query":"如何用SQL实现Lambda表达式？请给出示例代码。（请给出示例）","label":"通用知识"}
{"query":"JAVA全栈是否提供项目实战与源码？","label":"专业咨询"}
{"query":"产品经理速成是否提供项目实战与源码？（企业内训咨询）","label":"专业咨询"}
{"query":"如何用SQL实现特征工程？请给出示例代码。（请给出示例）","label":"通用知识"}
{"query":"JAVA全栈在上海有校区吗？（面向在职人员）","label":"专业咨询"}
{"query":"云原生工程师在武汉有校区吗？（含就业保障）","label":"专业咨询"}
{"query":"Python数据分析在北京有校区吗？（含就业保障）","label":"专业咨询"}
{"query":"数据库与运维在成都有校区吗？","label":"专业咨询"}
{"query":"JAVA全栈有无就业推荐与岗前辅导？（面向初中级学员）","label":"专业咨询"}
{"query":"什么是消息队列原理？请用通俗语言解释。（含复杂度分析）","label":"通用知识"}
{"query":"大数据工程师是否提供项目实战与源码？（面向初中级学员）","label":"专业咨询"}
{"query":"大数据工程师的退款与退费流程是怎样的？（面向在职人员）","label":"专业咨询"}
{"query":"JAVA全栈的退款与退费流程是怎样的？（面向在职人员）","label":"专业咨询"}
{"query":"如何在Docker中使用Lambda表达式？","label":"通用知识"}
{"query":"JAVA全栈的退款与退费流程是怎样的？（企业内训咨询）","label":"专业咨询"}
{"query":"Python数据分析在苏州有校区吗？（企业内训咨询）","label":"专业咨询"}
{"query":"如何在Redis中使用A*搜索算法？（请给出示例）","label":"通用知识"}
{"query":"JAVA全栈在北京有校区吗？（企业内训咨询）","label":"专业咨询"}
{"query":"如何在Redis中使用RMSE和MAE？（含示例代码）","label":"通用知识"}
{"query":"前端开发有无就业推荐与岗前辅导？（含就业保障）","label":"专业咨询"}
{"query":"如何用C++实现哈希表？请给出示例代码。（通俗解释）","label":"通用知识"}
{"query":"机器学习实战是否提供项目实战与源码？","label":"专业咨询"}
{"query":"全栈工程师班的退款与退费流程是怎样的？（企业内训咨询）","label":"专业咨询"}
{"query":"产品经理速成是否提供项目实战与源码？","label":"专业咨询"}
{"query":"如何在Jenkins中使用闭包？（请给出示例）","label":"通用知识"}
{"query":"请写出SQL中分布式事务的最佳实践。","label":"通用知识"}
{"query":"数据库与运维的上课时间和周期是怎样的？（面向在职人员）","label":"专业咨询"}
{"query":"什么是Docker镜像构建？请用通俗语言解释。（含示例代码）","label":"通用知识"}
{"query":"请比较快速排序和单例模式的区别。（含示例代码）","label":"通用知识"}
{"query":"全栈工程师班在上海有校区吗？","label":"专业咨询"}
{"query":"数据库与运维有无就业推荐与岗前辅导？（企业内训咨询）","label":"专业咨询"}
{"query":"JAVA全栈的退款与退费流程是怎样的？（含就业保障）","label":"专业咨询"}
{"query":"解释什么是归并排序并给出示例代码。（请给出示例）","label":"通用知识"}
{"query":"请写出Bash中HTTPS加密流程的最佳实践。（含示例代码）","label":"通用知识"}
{"query":"请比较缓存穿透和线程同步的区别。（含示例代码）","label":"通用知识"}
{"query":"移动开发是否支持分期付款或企业团报优惠？（含就业保障）","label":"专业咨询"}
{"query":"给出一个归并排序的实际例子并分析。（含复杂度分析）","label":"通用知识"}
{"query":"请说明线性回归的原理和应用。（通俗解释）","label":"通用知识"}
{"query":"如何优化贪心算法的性能？","label":"通用知识"}
{"query":"解释什么是HTTPS加密流程并给出示例代码。（请给出示例）","label":"通用知识"}
{"query":"解释什么是K-means聚类并给出示例代码。（请给出示例）","label":"通用知识"}
{"query":"机器学习实战在上海有校区吗？（企业内训咨询）","label":"专业咨询"}
{"query":"请写出Go中复数模与辐角的最佳实践。（含示例代码）","label":"通用知识"}
{"query":"如何在PyCharm中使用K折交叉验证？","label":"通用知识"}
{"query":"如何在Kubernetes集群下调试支持向量机相关问题？（请给出示例）","label":"通用知识"}
{"query":"给出一个单例模式的实际例子并分析。（含复杂度分析）","label":"通用知识"}
{"query":"如何在PyCharm中使用PCA主成分分析？（通俗解释）","label":"通用知识"}
{"query":"如何用Java实现图的最短路径？请给出示例代码。（请给出示例）","label":"通用知识"}
{"query":"解释什么是卷积神经网络并给出示例代码。（含复杂度分析）","label":"通用知识"}
{"query":"AI工程师实战班在上海有校区吗？","label":"专业咨询"}
{"query":"如何优化拓扑排序的性能？（通俗解释）","label":"通用知识"}
{"query":"Python数据分析在深圳有校区吗？（企业内训咨询）","label":"专业咨询"}
{"query":"如何优化A*搜索算法的性能？（请给出示例）","label":"通用知识"}
{"query":"Python数据分析培训学费是多少？（含就业保障）","label":"专业咨询"}
{"query":"如何优化信息熵的性能？（通俗解释）","label":"通用知识"}
{"query":"测试工程师的上课时间和周期是怎样的？（面向在职人员）","label":"专业咨询"}
{"query":"前端开发课程的大纲是什么？（面向在职人员）","label":"专业咨询"}
{"query":"测试工程师是否提供项目实战与源码？（企业内训咨询）","label":"专业咨询"}
{"query":"如何用Rust实现归并排序？请给出示例代码。（含示例代码）","label":"通用知识"}
{"query":"解释什么是动态规划并给出示例代码。（通俗解释）","label":"通用知识"}
{"query":"云原生工程师培训学费是多少？（含就业保障）","label":"专业咨询"}
{"query":"前端开发是否提供项目实战与源码？（面向在职人员）","label":"专业咨询"}
{"query":"请说明虚拟内存的原理和应用。（含示例代码）","label":"通用知识"}
{"query":"测试工程师培训学费是多少？","label":"专业咨询"}
{"query":"数据库与运维是否支持分期付款或企业团报优惠？（面向初中级学员）","label":"专业咨询"}
{"query":"全栈工程师班是否支持分期付款或企业团报优惠？（企业内训咨询）","label":"专业咨询"}
{"query":"如何在Jenkins中使用快速排序？（含复杂度分析）","label":"通用知识"}
{"query":"如何用Python实现信息熵？请给出示例代码。（通俗解释）","label":"通用知识"}
{"query":"如何用Rust实现Lambda表达式？请给出示例代码。（请给出示例）","label":"通用知识"}
{"query":"产品经理速成课程的大纲是什么？（含就业保障）","label":"专业咨询"}
{"query":"如何优化K折交叉验证的性能？（含复杂度分析）","label":"通用知识"}
{"query":"给出一个哈希表的实际例子并分析。（含复杂度分析）","label":"通用知识"}
{"query":"AI工程师实战班是否支持分期付款或企业团报优惠？（含就业保障）","label":"专业咨询"}
{"query":"请比较随机森林和A*搜索算法的区别。（含复杂度分析）","label":"通用知识"}
{"query":"前端开发是否提供面授或线上直播？（面向在职人员）","label":"专业咨询"}
{"query":"如何在Linux下调试OAuth认证相关问题？（含复杂度分析）","label":"通用知识"}
{"query":"AI工程师实战班有无就业推荐与岗前辅导？（面向在职人员）","label":"专业咨询"}
{"query":"JAVA全栈师资力量由谁组成？（是否有企业讲师）（企业内训咨询）","label":"专业咨询"}
{"query":"大数据工程师在杭州有校区吗？（面向初中级学员）","label":"专业咨询"}
{"query":"AI工程师实战班有无就业推荐与岗前辅导？（面向初中级学员）","label":"专业咨询"}
{"query":"大数据工程师的退款与退费流程是怎样的？（面向初中级学员）","label":"专业咨询"}
{"query":"数据库与运维在杭州有校区吗？（含就业保障）","label":"专业咨询"}
{"query":"云原生工程师是否支持分期付款或企业团报优惠？（企业内训咨询）","label":"专业咨询"}
{"query":"云原生工程师培训学费是多少？","label":"专业咨询"}
{"query":"什么是RMSE和MAE？请用通俗语言解释。（通俗解释）","label":"通用知识"}
{"query":"如何在MacOS下调试回溯算法相关问题？（含复杂度分析）","label":"通用知识"}
{"query":"机器学习实战的上课时间和周期是怎样的？","label":"专业咨询"}
{"query":"请比较Kubernetes部署和TCP三次握手的区别。（含示例代码）","label":"通用知识"}
{"query":"如何优化二分查找的性能？（含示例代码）","label":"通用知识"}
{"query":"给出一个贝叶斯定理的实际例子并分析。（含示例代码）","label":"通用知识"}
{"query":"全栈工程师班在苏州有校区吗？（含就业保障）","label":"专业咨询"}
{"query":"请说明梯度下降的原理和应用。（含复杂度分析）","label":"通用知识"}
{"query":"请比较LRU缓存和OAuth认证的区别。","label":"通用知识"}
{"query":"请说明正则表达式的贪婪匹配的原理和应用。","label":"通用知识"}
{"query":"数据库与运维在重庆有校区吗？（含就业保障）","label":"专业咨询"}
{"query":"什么是单例模式？请用通俗语言解释。（请给出示例）","label":"通用知识"}
{"query":"测试工程师是否提供项目实战与源码？（含就业保障）","label":"专业咨询"}
{"query":"大数据工程师在南京有校区吗？（面向初中级学员）","label":"专业咨询"}
{"query":"给出一个逻辑回归的实际例子并分析。（含示例代码）","label":"通用知识"}
{"query":"AI工程师实战班是否提供面授或线上直播？（含就业保障）","label":"专业咨询"}
{"query":"给出一个HTTPS加密流程的实际例子并分析。","label":"通用知识"}
{"query":"AI工程师实战班培训学费是多少？（含就业保障）","label":"专业咨询"}
{"query":"数据库与运维师资力量由谁组成？（是否有企业讲师）（面向初中级学员）","label":"专业咨询"}
{"query":"请说明决策树的原理和应用。","label":"通用知识"}
{"query":"如何在Git中使用二分查找？","label":"通用知识"}
{"query":"机器学习实战是否提供面授或线上直播？（含就业保障）","label":"专业咨询"}
{"query":"全栈工程师班课程的大纲是什么？","label":"专业咨询"}
{"query":"机器学习实战是否提供项目实战与源码？（含就业保障）","label":"专业咨询"}
{"query":"什么是卷积神经网络？请用通俗语言解释。","label":"通用知识"}
{"query":"如何在Kubernetes集群下调试互斥锁相关问题？（含示例代码）","label":"通用知识"}
{"query":"大数据工程师培训学费是多少？（企业内训咨询）","label":"专业咨询"}
{"query":"什么是支持向量机？请用通俗语言解释。（通俗解释）","label":"通用知识"}
{"query":"请比较闭包和单例模式的区别。（通俗解释）","label":"通用知识"}
{"query":"云原生工程师的退款与退费流程是怎样的？（含就业保障）","label":"专业咨询"}
{"query":"给出一个复数模与辐角的实际例子并分析。（含示例代码）","label":"通用知识"}
{"query":"大数据工程师是否提供面授或线上直播？","label":"专业咨询"}
{"query":"大数据工程师在深圳有校区吗？（面向初中级学员）","label":"专业咨询"}
{"query":"如何在Kubernetes集群下调试互斥锁相关问题？","label":"通用知识"}
{"query":"数据库与运维培训学费是多少？（面向在职人员）","label":"专业咨询"}
{"query":"如何在Postman中使用单例模式？","label":"通用知识"}
{"query":"云原生工程师的上课时间和周期是怎样的？","label":"专业咨询"}
{"query":"测试工程师有无就业推荐与岗前辅导？（企业内训咨询）","label":"专业咨询"}
{"query":"请比较Kubernetes部署和快速排序的区别。（含示例代码）","label":"通用知识"}
{"query":"数据库与运维课程的大纲是什么？（面向在职人员）","label":"专业咨询"}
{"query":"请比较反向传播和Docker镜像构建的区别。（通俗解释）","label":"通用知识"}
{"query":"机器学习实战在上海有校区吗？（面向初中级学员）","label":"专业咨询"}
{"query":"产品经理速成师资力量由谁组成？（是否有企业讲师）（企业内训咨询）","label":"专业咨询"}
{"query":"请说明回溯算法的原理和应用。","label":"通用知识"}
{"query":"大数据工程师在上海有校区吗？（面向初中级学员）","label":"专业咨询"}
{"query":"请比较决策树和OAuth认证的区别。（含复杂度分析）","label":"通用知识"}
{"query":"如何用Go实现复利计算？请给出示例代码。（含示例代码）","label":"通用知识"}
{"query":"AI工程师实战班是否提供项目实战与源码？（面向初中级学员）","label":"专业咨询"}
{"query":"如何在Docker容器下调试正则表达式的贪婪匹配相关问题？（含复杂度分析）","label":"通用知识"}
{"query":"AI工程师实战班课程的大纲是什么？（企业内训咨询）","label":"专业咨询"}
{"query":"移动开发在武汉有校区吗？（含就业保障）","label":"专业咨询"}
{"query":"如何在Docker容器下调试正态分布相关问题？（请给出示例）","label":"通用知识"}
{"query":"数据库与运维是否提供面授或线上直播？（面向在职人员）","label":"专业咨询"}
{"query":"解释什么是线程同步并给出示例代码。（请给出示例）","label":"通用知识"}
{"query":"请比较复数模与辐角和卷积神经网络的区别。（含示例代码）","label":"通用知识"}
{"query":"机器学习实战培训学费是多少？（面向初中级学员）","label":"专业咨询"}
{"query":"给出一个K-means聚类的实际例子并分析。（含示例代码）","label":"通用知识"}
{"query":"请说明K折交叉验证的原理和应用。（请给出示例）","label":"通用知识"}
{"query":"请比较决策树和正则表达式的区别。","label":"通用知识"}
{"query":"给出一个消息队列原理的实际例子并分析。","label":"通用知识"}
{"query":"Python数据分析师资力量由谁组成？（是否有企业讲师）（企业内训咨询）","label":"专业咨询"}
{"query":"给出一个回溯算法的实际例子并分析。","label":"通用知识"}
{"query":"给出一个图的最短路径的实际例子并分析。（含复杂度分析）","label":"通用知识"}
{"query":"如何优化信息熵的性能？","label":"通用知识"}
{"query":"前端开发师资力量由谁组成？（是否有企业讲师）","label":"专业咨询"}
{"query":"JAVA全栈的退款与退费流程是怎样的？（面向初中级学员）","label":"专业咨询"}
{"query":"JAVA全栈课程的大纲是什么？（含就业保障）","label":"专业咨询"}
{"query":"请写出Rust中OAuth认证的最佳实践。（通俗解释）","label":"通用知识"}
{"query":"全栈工程师班师资力量由谁组成？（是否有企业讲师）（含就业保障）","label":"专业咨询"}
{"query":"产品经理速成在重庆有校区吗？（含就业保障）","label":"专业咨询"}
{"query":"AI工程师实战班的上课时间和周期是怎样的？（含就业保障）","label":"专业咨询"}
{"query":"如何用Bash实现正则表达式？请给出示例代码。（请给出示例）","label":"通用知识"}
{"query":"产品经理速成的上课时间和周期是怎样的？（含就业保障）","label":"专业咨询"}
{"query":"JAVA全栈的上课时间和周期是怎样的？（面向初中级学员）","label":"专业咨询"}
{"query":"如何在Postman中使用拓扑排序？（含复杂度分析）","label":"通用知识"}
{"query":"给出一个Kubernetes部署的实际例子并分析。（通俗解释）","label":"通用知识"}
{"query":"大数据工程师培训学费是多少？（面向在职人员）","label":"专业咨询"}
{"query":"请写出SQL中回溯算法的最佳实践。（通俗解释）","label":"通用知识"}
{"query":"Python数据分析培训学费是多少？","label":"专业咨询"}
{"query":"如何在MacOS下调试矩阵求逆相关问题？（通俗解释）","label":"通用知识"}
{"query":"Python数据分析培训学费是多少？（企业内训咨询）","label":"专业咨询"}
{"query":"云原生工程师是否支持分期付款或企业团报优惠？","label":"专业咨询"}
{"query":"请比较缓存穿透和PCA主成分分析的区别。（请给出示例）","label":"通用知识"}
{"query":"数据库与运维的退款与退费流程是怎样的？","label":"专业咨询"}
{"query":"如何在PyCharm中使用信号量？（含复杂度分析）","label":"通用知识"}
{"query":"测试工程师有无就业推荐与岗前辅导？（面向在职人员）","label":"专业咨询"}
{"query":"如何用Rust实现矩阵求逆？请给出示例代码。","label":"通用知识"}
{"query":"什么是支持向量机？请用通俗语言解释。（请给出示例）","label":"通用知识"}
{"query":"给出一个Docker镜像构建的实际例子并分析。（通俗解释）","label":"通用知识"}
{"query":"云原生工程师师资力量由谁组成？（是否有企业讲师）（企业内训咨询）","label":"专业咨询"}
{"query":"大数据工程师师资力量由谁组成？（是否有企业讲师）（面向在职人员）","label":"专业咨询"}
{"query":"大数据工程师有无就业推荐与岗前辅导？（企业内训咨询）","label":"专业咨询"}
{"query":"请写出Java中互斥锁的最佳实践。（通俗解释）","label":"通用知识"}
{"query":"请写出C++中单例模式的最佳实践。（含复杂度分析）","label":"通用知识"}
{"query":"如何优化信号量的性能？（含示例代码）","label":"通用知识"}
{"query":"机器学习实战在深圳有校区吗？","label":"专业咨询"}
{"query":"Python数据分析课程的大纲是什么？","label":"专业咨询"}
{"query":"请写出Go中RESTful API的最佳实践。","label":"通用知识"}
{"query":"请比较正态分布和回溯算法的区别。","label":"通用知识"}
{"query":"全栈工程师班的上课时间和周期是怎样的？","label":"专业咨询"}
{"query":"产品经理速成课程的大纲是什么？（面向初中级学员）","label":"专业咨询"}
{"query":"机器学习实战师资力量由谁组成？（是否有企业讲师）（面向初中级学员）","label":"专业咨询"}
{"query":"如何优化信号量的性能？（通俗解释）","label":"通用知识"}
{"query":"如何在Linux下调试Kubernetes部署相关问题？（通俗解释）","label":"通用知识"}
{"query":"如何用JavaScript实现OAuth认证？请给出示例代码。","label":"通用知识"}
{"query":"请写出Python中哈希表的最佳实践。（含复杂度分析）","label":"通用知识"}
{"query":"测试工程师是否提供面授或线上直播？（面向初中级学员）","label":"专业咨询"}
{"query":"请说明贪心算法的原理和应用。（含示例代码）","label":"通用知识"}
{"query":"请比较归并排序和HTTPS加密流程的区别。（请给出示例）","label":"通用知识"}
{"query":"什么是哈希表？请用通俗语言解释。","label":"通用知识"}
{"query":"大数据工程师师资力量由谁组成？（是否有企业讲师）（企业内训咨询）","label":"专业咨询"}
{"query":"测试工程师是否支持分期付款或企业团报优惠？（面向初中级学员）","label":"专业咨询"}
{"query":"测试工程师是否提供项目实战与源码？","label":"专业咨询"}
{"query":"请说明K-means聚类的原理和应用。（含复杂度分析）","label":"通用知识"}
{"query":"全栈工程师班是否支持分期付款或企业团报优惠？（面向初中级学员）","label":"专业咨询"}
{"query":"大数据工程师是否提供面授或线上直播？（面向在职人员）","label":"专业咨询"}
{"query":"给出一个决策树的实际例子并分析。（含示例代码）","label":"通用知识"}
{"query":"机器学习实战师资力量由谁组成？（是否有企业讲师）（含就业保障）","label":"专业咨询"}
{"query":"前端开发是否提供项目实战与源码？（企业内训咨询）","label":"专业咨询"}
{"query":"请说明TCP三次握手的原理和应用。（含示例代码）","label":"通用知识"}
{"query":"Python数据分析是否提供面授或线上直播？","label":"专业咨询"}
{"query":"Python数据分析的上课时间和周期是怎样的？（企业内训咨询）","label":"专业咨询"}
{"query":"如何在Linux下调试二叉树遍历相关问题？（含示例代码）","label":"通用知识"}
{"query":"给出一个线性回归的实际例子并分析。（含复杂度分析）","label":"通用知识"}
{"query":"测试工程师的上课时间和周期是怎样的？（面向初中级学员）","label":"专业咨询"}
{"query":"如何用JavaScript实现混淆矩阵？请给出示例代码。（请给出示例）","label":"通用知识"}
{"query":"如何用Go实现OAuth认证？请给出示例代码。","label":"通用知识"}
{"query":"请比较二分查找和快速排序的区别。（请给出示例）","label":"通用知识"}
{"query":"大数据工程师是否提供面授或线上直播？（含就业保障）","label":"专业咨询"}
{"query":"前端开发的上课时间和周期是怎样的？（含就业保障）","label":"专业咨询"}
{"query":"全栈工程师班师资力量由谁组成？（是否有企业讲师）","label":"专业咨询"}
{"query":"什么是贝叶斯定理？请用通俗语言解释。","label":"通用知识"}
{"query":"移动开发课程的大纲是什么？（面向在职人员）","label":"专业咨询"}
{"query":"请说明消息队列原理的原理和应用。（通俗解释）","label":"通用知识"}
{"query":"Python数据分析是否提供项目实战与源码？（面向初中级学员）","label":"专业咨询"}
{"query":"请写出Go中Docker镜像构建的最佳实践。（请给出示例）","label":"通用知识"}
{"query":"机器学习实战的退款与退费流程是怎样的？","label":"专业咨询"}
{"query":"如何用Java实现支持向量机？请给出示例代码。（请给出示例）","label":"通用知识"}
{"query":"解释什么是支持向量机并给出示例代码。（含复杂度分析）","label":"通用知识"}
{"query":"给出一个K折交叉验证的实际例子并分析。（含示例代码）","label":"通用知识"}
{"query":"请写出Rust中矩阵求逆的最佳实践。（通俗解释）","label":"通用知识"}
{"query":"AI工程师实战班的退款与退费流程是怎样的？（面向初中级学员）","label":"专业咨询"}
{"query":"前端开发的退款与退费流程是怎样的？（企业内训咨询）","label":"专业咨询"}
{"query":"解释什么是PCA主成分分析并给出示例代码。（通俗解释）","label":"通用知识"}
{"query":"如何在MacOS下调试OAuth认证相关问题？（请给出示例）","label":"通用知识"}
{"query":"数据库与运维有无就业推荐与岗前辅导？（面向初中级学员）","label":"专业咨询"}
{"query":"机器学习实战是否提供面授或线上直播？（面向在职人员）","label":"专业咨询"}
{"query":"如何在Git中使用A*搜索算法？（通俗解释）","label":"通用知识"}
{"query":"什么是缓存穿透？请用通俗语言解释。（含复杂度分析）","label":"通用知识"}
{"query":"给出一个随机森林的实际例子并分析。（请给出示例）","label":"通用知识"}
{"query":"如何用Rust实现Docker镜像构建？请给出示例代码。（含示例代码）","label":"通用知识"}
{"query":"如何在Docker容器下调试图的最短路径相关问题？（含复杂度分析）","label":"通用知识"}
{"query":"全栈工程师班是否支持分期付款或企业团报优惠？","label":"专业咨询"}
{"query":"Python数据分析是否支持分期付款或企业团报优惠？（面向在职人员）","label":"专业咨询"}
{"query":"AI工程师实战班的上课时间和周期是怎样的？","label":"专业咨询"}
{"query":"如何优化正态分布的性能？（含示例代码）","label":"通用知识"}
{"query":"如何在MacOS下调试复利计算相关问题？（含复杂度分析）","label":"通用知识"}
{"query":"测试工程师有无就业推荐与岗前辅导？","label":"专业咨询"}
{"query":"移动开发培训学费是多少？（含就业保障）","label":"专业咨询"}
{"query":"如何用C++实现贪心算法？请给出示例代码。（含复杂度分析）","label":"通用知识"}
{"query":"云原生工程师课程的大纲是什么？（企业内训咨询）","label":"专业咨询"}
{"query":"AI工程师实战班是否支持分期付款或企业团报优惠？","label":"专业咨询"}
{"query":"数据库与运维师资力量由谁组成？（是否有企业讲师）（企业内训咨询）","label":"专业咨询"}
{"query":"请说明闭包的原理和应用。（请给出示例）","label":"通用知识"}
{"query":"如何在Docker容器下调试RPC原理相关问题？（请给出示例）","label":"通用知识"}
{"query":"什么是动态规划？请用通俗语言解释。（请给出示例）","label":"通用知识"}
{"query":"JAVA全栈师资力量由谁组成？（是否有企业讲师）（含就业保障）","label":"专业咨询"}
{"query":"请说明混淆矩阵的原理和应用。（通俗解释）","label":"通用知识"}
{"query":"Python数据分析有无就业推荐与岗前辅导？（含就业保障）","label":"专业咨询"}
{"query":"如何用Java实现Kubernetes部署？请给出示例代码。（请给出示例）","label":"通用知识"}
{"query":"机器学习实战在成都有校区吗？","label":"专业咨询"}
{"query":"机器学习实战在广州有校区吗？（企业内训咨询）","label":"专业咨询"}
{"query":"什么是OAuth认证？请用通俗语言解释。（含复杂度分析）","label":"通用知识"}
{"query":"云原生工程师的退款与退费流程是怎样的？","label":"专业咨询"}
{"query":"前端开发的上课时间和周期是怎样的？（企业内训咨询）","label":"专业咨询"}
{"query":"全栈工程师班是否支持分期付款或企业团报优惠？（面向在职人员）","label":"专业咨询"}
{"query":"产品经理速成课程的大纲是什么？","label":"专业咨询"}
{"query":"如何在Jenkins中使用K折交叉验证？","label":"通用知识"}
{"query":"如何用C++实现线程同步？请给出示例代码。（含复杂度分析）","label":"通用知识"}
{"query":"请比较单例模式和归并排序的区别。","label":"通用知识"}
{"query":"请写出Bash中信号量的最佳实践。（通俗解释）","label":"通用知识"}
{"query":"请说明二叉树遍历的原理和应用。（含复杂度分析）","label":"通用知识"}
{"query":"请写出JavaScript中混淆矩阵的最佳实践。（含复杂度分析）","label":"通用知识"}
{"query":"什么是特征工程？请用通俗语言解释。（请给出示例）","label":"通用知识"}
{"query":"如何在Redis中使用正则表达式的贪婪匹配？（含示例代码）","label":"通用知识"}
{"query":"如何用Java实现卷积神经网络？请给出示例代码。","label":"通用知识"}
{"query":"AI工程师实战班在广州有校区吗？（面向初中级学员）","label":"专业咨询"}
{"query":"全栈工程师班师资力量由谁组成？（是否有企业讲师）（面向在职人员）","label":"专业咨询"}
{"query":"如何在Redis中使用混淆矩阵？（含示例代码）","label":"通用知识"}
{"query":"请说明RMSE和MAE的原理和应用。（含示例代码）","label":"通用知识"}
{"query":"如何在Linux下调试特征工程相关问题？（通俗解释）","label":"通用知识"}
{"query":"JAVA全栈课程的大纲是什么？（企业内训咨询）","label":"专业咨询"}
{"query":"前端开发是否提供面授或线上直播？（企业内训咨询）","label":"专业咨询"}
{"query":"给出一个闭包的实际例子并分析。（含示例代码）","label":"通用知识"}
{"query":"Python数据分析的退款与退费流程是怎样的？","label":"专业咨询"}
{"query":"AI工程师实战班课程的大纲是什么？（面向初中级学员）","label":"专业咨询"}
{"query":"JAVA全栈师资力量由谁组成？（是否有企业讲师）（面向在职人员）","label":"专业咨询"}
{"query":"数据库与运维的退款与退费流程是怎样的？（企业内训咨询）","label":"专业咨询"}
{"query":"如何在Linux下调试线性回归相关问题？（含复杂度分析）","label":"通用知识"}
{"query":"云原生工程师的退款与退费流程是怎样的？（面向初中级学员）","label":"专业咨询"}
{"query":"AI工程师实战班是否支持分期付款或企业团报优惠？（面向初中级学员）","label":"专业咨询"}
{"query":"什么是复数模与辐角？请用通俗语言解释。（含示例代码）","label":"通用知识"}
{"query":"数据库与运维是否提供面授或线上直播？（面向初中级学员）","label":"专业咨询"}
{"query":"请说明LRU缓存的原理和应用。","label":"通用知识"}
{"query":"Python数据分析在杭州有校区吗？","label":"专业咨询"}
{"query":"测试工程师师资力量由谁组成？（是否有企业讲师）（面向初中级学员）","label":"专业咨询"}
{"query":"如何在Git中使用拓扑排序？（通俗解释）","label":"通用知识"}
{"query":"云原生工程师课程的大纲是什么？","label":"专业咨询"}
{"query":"数据库与运维课程的大纲是什么？（企业内训咨询）","label":"专业咨询"}
{"query":"解释什么是PCA主成分分析并给出示例代码。（请给出示例）","label":"通用知识"}
{"query":"如何用C++实现RMSE和MAE？请给出示例代码。（请给出示例）","label":"通用知识"}
{"query":"给出一个正态分布的实际例子并分析。（请给出示例）","label":"通用知识"}
{"query":"给出一个梯度下降的实际例子并分析。（含示例代码）","label":"通用知识"}
{"query":"全栈工程师班是否提供项目实战与源码？（面向在职人员）","label":"专业咨询"}
{"query":"测试工程师在北京有校区吗？（面向在职人员）","label":"专业咨询"}
{"query":"产品经理速成的上课时间和周期是怎样的？（面向初中级学员）","label":"专业咨询"}
{"query":"如何用Java实现正则表达式？请给出示例代码。（请给出示例）","label":"通用知识"}
{"query":"数据库与运维课程的大纲是什么？（含就业保障）","label":"专业咨询"}
{"query":"云原生工程师师资力量由谁组成？（是否有企业讲师）（含就业保障）","label":"专业咨询"}
{"query":"如何在Jenkins中使用消息队列原理？","label":"通用知识"}
{"query":"Python数据分析在南京有校区吗？（面向初中级学员）","label":"专业咨询"}
{"query":"测试工程师在北京有校区吗？","label":"专业咨询"}
{"query":"解释什么是Lambda表达式并给出示例代码。（含示例代码）","label":"通用知识"}
{"query":"请说明卷积神经网络的原理和应用。（含示例代码）","label":"通用知识"}
